.gitignore
MANIFEST.in
README.txt
setup.cfg
setup.py
collective/__init__.py
collective.z3cform.addablechoice.egg-info/PKG-INFO
collective.z3cform.addablechoice.egg-info/SOURCES.txt
collective.z3cform.addablechoice.egg-info/dependency_links.txt
collective.z3cform.addablechoice.egg-info/entry_points.txt
collective.z3cform.addablechoice.egg-info/namespace_packages.txt
collective.z3cform.addablechoice.egg-info/not-zip-safe
collective.z3cform.addablechoice.egg-info/requires.txt
collective.z3cform.addablechoice.egg-info/top_level.txt
collective/z3cform/__init__.py
collective/z3cform/addablechoice/README.txt
collective/z3cform/addablechoice/__init__.py
collective/z3cform/addablechoice/configure.zcml
collective/z3cform/addablechoice/display.pt
collective/z3cform/addablechoice/input.pt
collective/z3cform/addablechoice/interfaces.py
collective/z3cform/addablechoice/tests.py
collective/z3cform/addablechoice/widget.py
collective/z3cform/addablechoice/profiles/testing/catalog.xml
docs/HISTORY.txt