Metadata-Version: 1.0
Name: collective.z3cform.addablechoice
Version: 0.3
Summary: Adds a choice widget with text field to z3cform.
Home-page: http://pypi.python.org/pypi/collective.z3cform.addablechoice
Author: Johan Beyers
Author-email: jbeyers@juizi.com
License: GPL
Keywords: syslab choice widget z3cform
Platform: UNKNOWN
Classifier: Programming Language :: Python
Classifier: Topic :: Software Development :: Libraries :: Python Modules
